tests/__init__.py
tests/test_commands.py
tests/test_serializers.py
tests/test_services.py
umbrella_cli/__init__.py
umbrella_cli/cli.py
umbrella_cli/models.py
umbrella_cli/serializers.py
umbrella_cli/services.py
umbrella_cli/commands/__init__.py
umbrella_cli/commands/cmd_internal_networks.py
umbrella_cli/commands/cmd_sites.py
cisco_umbrella_cli-0.2.dist-info/LICENSE
cisco_umbrella_cli-0.2.dist-info/METADATA
cisco_umbrella_cli-0.2.dist-info/WHEEL
cisco_umbrella_cli-0.2.dist-info/entry_points.txt
cisco_umbrella_cli-0.2.dist-info/top_level.txt
cisco_umbrella_cli-0.2.dist-info/RECORD
